kinde_fastapi/__init__.py
kinde_fastapi/examples/example_app.py
kinde_fastapi/examples/management_token_example.py
kinde_fastapi/examples/session.py
kinde_fastapi/framework/__init__.py
kinde_fastapi/framework/fastapi_framework.py
kinde_fastapi/framework/fastapi_framework_factory.py
kinde_fastapi/middleware/framework_middleware.py
kinde_fastapi/storage/fastapi_storage.py
kinde_fastapi/storage/fastapi_storage_factory.py
kinde_flask/__init__.py
kinde_flask/examples/example_app.py
kinde_flask/framework/flask_framework.py
kinde_flask/framework/flask_framework_factory.py
kinde_flask/middleware/framework_middleware.py
kinde_flask/storage/flask_storage_factory.py
kinde_python_sdk-2.2.0.dist-info/licenses/LICENSE
kinde_sdk/__init__.py
kinde_sdk/auth/__init__.py
kinde_sdk/auth/api_options.py
kinde_sdk/auth/async_claims.py
kinde_sdk/auth/async_oauth.py
kinde_sdk/auth/base_auth.py
kinde_sdk/auth/base_oauth.py
kinde_sdk/auth/claims.py
kinde_sdk/auth/config_loader.py
kinde_sdk/auth/entitlements.py
kinde_sdk/auth/enums.py
kinde_sdk/auth/feature_flags.py
kinde_sdk/auth/login_options.py
kinde_sdk/auth/oauth.py
kinde_sdk/auth/permissions.py
kinde_sdk/auth/portals.py
kinde_sdk/auth/roles.py
kinde_sdk/auth/smart_oauth.py
kinde_sdk/auth/token_manager.py
kinde_sdk/auth/tokens.py
kinde_sdk/auth/user_session.py
kinde_sdk/core/__init__.py
kinde_sdk/core/exceptions.py
kinde_sdk/core/helpers.py
kinde_sdk/core/session_management.py
kinde_sdk/core/framework/__init__.py
kinde_sdk/core/framework/framework_context.py
kinde_sdk/core/framework/framework_factory.py
kinde_sdk/core/framework/framework_interface.py
kinde_sdk/core/framework/null_framework.py
kinde_sdk/core/storage/__init__.py
kinde_sdk/core/storage/framework_aware_storage.py
kinde_sdk/core/storage/local_storage.py
kinde_sdk/core/storage/memory_storage.py
kinde_sdk/core/storage/storage_factory.py
kinde_sdk/core/storage/storage_interface.py
kinde_sdk/core/storage/storage_manager.py
kinde_sdk/frontend/__init__.py
kinde_sdk/frontend/api_client.py
kinde_sdk/frontend/api_response.py
kinde_python_sdk-2.2.0.dist-info/METADATA
kinde_python_sdk-2.2.0.dist-info/WHEEL
kinde_python_sdk-2.2.0.dist-info/top_level.txt
kinde_python_sdk-2.2.0.dist-info/RECORD
