Metadata-Version: 2.4
Name: kinde-python-sdk
Version: 2.2.0
Summary: Connect your app to the Kinde platform
Author-email: Kinde Engineering <engineering@kinde.com>
Project-URL: Homepage, https://github.com/kinde-oss/kinde-python-sdk
Classifier: Development Status :: 5 - Production/Stable
Classifier: License :: OSI Approved :: MIT License
Classifier: Natural Language :: English
Classifier: Operating System :: OS Independent
Classifier: Programming Language :: Python
Classifier: Programming Language :: Python :: 3.9
Classifier: Programming Language :: Python :: 3.10
Classifier: Programming Language :: Python :: 3.11
Classifier: Programming Language :: Python :: 3.12
Classifier: Programming Language :: Python :: 3.13
Requires-Python: >=3.9
License-File: LICENSE
Requires-Dist: urllib3<3.0,>=2.2.0
Requires-Dist: python-dateutil<3.0,>=2.9.0
Requires-Dist: Authlib<2.0,>=1.3.0
Requires-Dist: pyjwt<3.0,>=2.10.0
Requires-Dist: requests<3.0,>=2.32.2
Requires-Dist: typing-extensions<5.0,>=4.11.0
Requires-Dist: frozendict<3.0,>=2.4.3
Requires-Dist: certifi<2025.0.0,>=2024.2.2
Requires-Dist: PyYAML<7.0.0,>=6.0.1
Requires-Dist: cryptography<42.0.0,>=41.0.0
Requires-Dist: python-dotenv<2.0.0,>=1.0.0
Requires-Dist: itsdangerous<3.0.0,>=2.2.0
Requires-Dist: nest-asyncio<2.0.0,>=1.5.8
Requires-Dist: httpx<0.29.0,>=0.25.0
Requires-Dist: pydantic<3.0.0,>=2.0.0
Provides-Extra: fastapi
Requires-Dist: fastapi<1.0.0,>=0.110.0; extra == "fastapi"
Requires-Dist: python-multipart<1.0.0,>=0.0.6; extra == "fastapi"
Requires-Dist: uvicorn<0.26.0,>=0.25.0; extra == "fastapi"
Provides-Extra: flask
Requires-Dist: flask<4.0.0,>=3.0.0; extra == "flask"
Dynamic: license-file
